cricheroes/__init__.py
cricheroes/cricheroes.py
cricheroes-1.0.10.dist-info/LICENSE
cricheroes-1.0.10.dist-info/METADATA
cricheroes-1.0.10.dist-info/WHEEL
cricheroes-1.0.10.dist-info/top_level.txt
cricheroes-1.0.10.dist-info/RECORD
