Metadata-Version: 2.1
Name: cricheroes
Version: 1.0.10
Summary: Python APIs to fetch and store team data from cricheroes.in
Home-page: https://github.com/pupattan/cricheroes
Author: pattap
Author-email: pulak.pattanayak@gmail.com
License: MIT
License-File: LICENSE
Requires-Dist: beautifulsoup4
Requires-Dist: python-dateutil
Requires-Dist: selenium
